{"organizations": [], "uuid": "d707d3ddb479489bf2b2ae193de507bcf34892be", "thread": {"social": {"gplus": {"shares": 0}, "pinterest": {"shares": 0}, "vk": {"shares": 0}, "linkedin": {"shares": 0}, "facebook": {"likes": 0, "shares": 0, "comments": 0}, "stumbledupon": {"shares": 0}}, "site_full": "www.tripadvisor.com", "main_image": "https://media-cdn.tripadvisor.com/media/photo-s/03/94/b9/b2/hotel-de-la-tour-eiffel.jpg", "site_section": "https://www.tripadvisor.com/Hotel_Review-g187147-d499907-Reviews-Hotel_de_la_Tour_Eiffel-Paris_Ile_de_France.html", "section_title": "Hotel de la Tour Eiffel - UPDATED 2017 Reviews &amp; Price Comparison (Paris, France) - TripAdvisor", "url": "https://www.tripadvisor.com/ShowUserReviews-g187147-d499907-r468414180-Hotel_de_la_Tour_Eiffel-Paris_Ile_de_France.html", "country": "US", "domain_rank": 189, "title": "Decent place with good location", "performance_score": 0, "site": "tripadvisor.com", "participants_count": 1, "title_full": "Decent place with good location - Review of Hotel de la Tour Eiffel, Paris, France - TripAdvisor", "spam_score": 0.0, "site_type": "discussions", "published": "2017-03-18T02:00:00.000+02:00", "replies_count": 0, "uuid": "d707d3ddb479489bf2b2ae193de507bcf34892be"}, "author": "Erik V", "url": "https://www.tripadvisor.com/ShowUserReviews-g187147-d499907-r468414180-Hotel_de_la_Tour_Eiffel-Paris_Ile_de_France.html", "ord_in_thread": 0, "title": "Decent place with good location", "locations": [], "entities": {"persons": [], "locations": [], "organizations": []}, "highlightText": "", "language": "english", "persons": [], "text": "This is an efficient, clean, and practical option for travellers wanting to stay walking distance to the Eiffel Tower. Stayed for 2 nights with no problems. Rooms are on the small side, but clean. Full private bathroom in each room. There was a breakfast option to purchase, but we skipped that, since there are plenty of places nearby to get coffee and pastries in the morning. The Eiffel Tower is about a 10 minute walk from the hotel. They contract with a car service to the airport, which was useful (cost is 18-20€ per person).\nWe would stay here again!", "external_links": [], "published": "2017-03-18T02:00:00.000+02:00", "crawled": "2017-03-27T21:48:33.321+03:00", "highlightTitle": ""}