{"organizations": [], "uuid": "450027881a8e6f2227c715557a5dac8f917bb743", "thread": {"social": {"gplus": {"shares": 0}, "pinterest": {"shares": 0}, "vk": {"shares": 0}, "linkedin": {"shares": 0}, "facebook": {"likes": 0, "shares": 0, "comments": 0}, "stumbledupon": {"shares": 0}}, "site_full": "www.tripadvisor.com", "main_image": "https://media-cdn.tripadvisor.com/media/photo-s/07/7e/96/4d/hotel-manfredi-suite.jpg", "site_section": "https://www.tripadvisor.com/Hotel_Review-g187791-d456489-Reviews-Hotel_Manfredi_Suite_in_Rome-Rome_Lazio.html", "section_title": "Hotel Manfredi Suite in Rome - UPDATED 2017 Reviews &amp; Price Comparison (Italy) - TripAdvisor", "url": "https://www.tripadvisor.com/ShowUserReviews-g187791-d456489-r470236648-Hotel_Manfredi_Suite_in_Rome-Rome_Lazio.html", "country": "US", "domain_rank": 189, "title": "Lovely Hotel Near Spanish Steps", "performance_score": 0, "site": "tripadvisor.com", "participants_count": 1, "title_full": "Lovely Hotel Near Spanish Steps - Review of Hotel Manfredi Suite in Rome, Rome, Italy - TripAdvisor", "spam_score": 0.006, "site_type": "discussions", "published": "2017-03-26T03:00:00.000+03:00", "replies_count": 0, "uuid": "450027881a8e6f2227c715557a5dac8f917bb743"}, "author": "jen1105", "url": "https://www.tripadvisor.com/ShowUserReviews-g187791-d456489-r470236648-Hotel_Manfredi_Suite_in_Rome-Rome_Lazio.html", "ord_in_thread": 0, "title": "Lovely Hotel Near Spanish Steps", "locations": [], "entities": {"persons": [], "locations": [], "organizations": []}, "highlightText": "", "language": "english", "persons": [], "text": "My daughter and I stayed 3 nights at the Hotel Manfredi Suite. The hotel is well situated on a charming street near the Spanish Steps and Metro. Our room was very comfortable and well appointed. The bathroom was well furnished with an amazing shower with many varieties of settings. The room had excellent air conditioning. The concierge was helpful in making dinner reservations. Also, the breakfast was excellent with wonderful food and coffee service. I highly recommend!", "external_links": ["https://static.tacdn.com/img2/x.gif"], "published": "2017-03-26T03:00:00.000+03:00", "crawled": "2017-03-28T15:14:41.727+03:00", "highlightTitle": ""}