{"organizations": [], "uuid": "50977bdbfa18c63177342e02ad4f9419adf55a95", "thread": {"social": {"gplus": {"shares": 0}, "pinterest": {"shares": 0}, "vk": {"shares": 0}, "linkedin": {"shares": 0}, "facebook": {"likes": 0, "shares": 0, "comments": 0}, "stumbledupon": {"shares": 0}}, "site_full": "www.tripadvisor.com", "main_image": "https://media-cdn.tripadvisor.com/media/photo-s/09/72/42/ab/bedroom.jpg", "site_section": "https://www.tripadvisor.com/Hotel_Review-g60763-d805827-Reviews-AKA_Central_Park-New_York_City_New_York.html", "section_title": "AKA Central Park - UPDATED 2017 Hotel Reviews &amp; Price Comparison (New York City) - TripAdvisor", "url": "https://www.tripadvisor.com/ShowUserReviews-g60763-d805827-r470363803-AKA_Central_Park-New_York_City_New_York.html", "country": "US", "domain_rank": 189, "title": "Superb room and location, fair price", "performance_score": 0, "site": "tripadvisor.com", "participants_count": 1, "title_full": "Superb room and location, fair price - Review of AKA Central Park, New York City, NY - TripAdvisor", "spam_score": 0.193, "site_type": "discussions", "published": "2017-03-26T03:00:00.000+03:00", "replies_count": 0, "uuid": "50977bdbfa18c63177342e02ad4f9419adf55a95"}, "author": "JBeechLBNY", "url": "https://www.tripadvisor.com/ShowUserReviews-g60763-d805827-r470363803-AKA_Central_Park-New_York_City_New_York.html", "ord_in_thread": 0, "title": "Superb room and location, fair price", "locations": [], "entities": {"persons": [], "locations": [], "organizations": []}, "highlightText": "", "language": "english", "persons": [], "text": "Booked this through Expedia some months' ago. Room was large, high end modern, everything was super clean and in great shape. Had views out to street, as well as an outdoor space (too cold to use). Lobby and hallways and elevator were hip and in great shape. Very comfortable bed.", "external_links": [], "published": "2017-03-26T03:00:00.000+03:00", "crawled": "2017-03-31T20:03:34.168+03:00", "highlightTitle": ""}