{"organizations": [], "uuid": "27114e2cd80a6c5235342421ba17c9e3f7ed4c4f", "thread": {"social": {"gplus": {"shares": 0}, "pinterest": {"shares": 0}, "vk": {"shares": 0}, "linkedin": {"shares": 0}, "facebook": {"likes": 0, "shares": 0, "comments": 0}, "stumbledupon": {"shares": 0}}, "site_full": "www.tripadvisor.com", "main_image": "https://media-cdn.tripadvisor.com/media/photo-s/09/b0/a3/68/the-nadler-victoria.jpg", "site_section": "https://www.tripadvisor.com/Hotel_Review-g186338-d8625676-Reviews-or10-The_Nadler_Victoria-London_England.html", "section_title": "The Nadler Victoria - UPDATED 2017 Hotel Reviews &amp; Price Comparison (London, England) - TripAdvisor", "url": "https://www.tripadvisor.com/ShowUserReviews-g186338-d8625676-r467294980-The_Nadler_Victoria-London_England.html", "country": "US", "domain_rank": 189, "title": "i'd give it 3.5 stars!", "performance_score": 0, "site": "tripadvisor.com", "participants_count": 1, "title_full": "i'd give it 3.5 stars! - Review of The Nadler Victoria, London, England - TripAdvisor", "spam_score": 0.004, "site_type": "discussions", "published": "2017-03-14T02:00:00.000+02:00", "replies_count": 0, "uuid": "27114e2cd80a6c5235342421ba17c9e3f7ed4c4f"}, "author": "Stav S", "url": "https://www.tripadvisor.com/ShowUserReviews-g186338-d8625676-r467294980-The_Nadler_Victoria-London_England.html", "ord_in_thread": 0, "title": "i'd give it 3.5 stars!", "locations": [], "entities": {"persons": [], "locations": [], "organizations": []}, "highlightText": "", "language": "english", "persons": [], "text": "the nadler victoria offers one one hand- a relatively cheap stay right next to buckingham palace- its very convenient to get to and from the city center.\nwe took the most basic room- which means there was no bath tub- on the plus side, the rooms are rather big and come with a kitchenette so you can make your own coffee (comes with a nespresso machine!) and your meals of you would like. in one side the room is filled with some nice gadget (smart TV and so on), on the other hand- the basic room is in an underground floor and the energy saving systems sometimes causes you to go outside into a dark hallway that will light up like in a horror movie :)\nthe staff is extremely helpful and friendly and make really good suggestions! so that's a huge plus :)\nRoom Tip: they are building right in front - ask for yard facing rooms... See more room tips", "external_links": [], "published": "2017-03-14T02:00:00.000+02:00", "crawled": "2017-03-30T02:04:00.971+03:00", "highlightTitle": ""}