{"organizations": [], "uuid": "092eb3cbb73cc27c5735a205c8951dce61ae9f77", "thread": {"social": {"gplus": {"shares": 0}, "pinterest": {"shares": 0}, "vk": {"shares": 0}, "linkedin": {"shares": 0}, "facebook": {"likes": 0, "shares": 0, "comments": 0}, "stumbledupon": {"shares": 0}}, "site_full": "www.tripadvisor.com", "main_image": "https://media-cdn.tripadvisor.com/media/photo-s/08/12/96/79/hotel-moliere.jpg", "site_section": "https://www.tripadvisor.com/Hotel_Review-g187147-d232545-Reviews-Hotel_Moliere-Paris_Ile_de_France.html", "section_title": "Hotel Moliere - UPDATED 2017 Reviews &amp; Price Comparison (Paris, France) - TripAdvisor", "url": "https://www.tripadvisor.com/ShowUserReviews-g187147-d232545-r470232267-Hotel_Moliere-Paris_Ile_de_France.html", "country": "US", "domain_rank": 189, "title": "Great Hotel in fantastic location", "performance_score": 0, "site": "tripadvisor.com", "participants_count": 1, "title_full": "Great Hotel in fantastic location - Review of Hotel Moliere, Paris, France - TripAdvisor", "spam_score": 0.028, "site_type": "discussions", "published": "2017-03-26T03:00:00.000+03:00", "replies_count": 0, "uuid": "092eb3cbb73cc27c5735a205c8951dce61ae9f77"}, "author": "tralli1234", "url": "https://www.tripadvisor.com/ShowUserReviews-g187147-d232545-r470232267-Hotel_Moliere-Paris_Ile_de_France.html", "ord_in_thread": 0, "title": "Great Hotel in fantastic location", "locations": [], "entities": {"persons": [], "locations": [], "organizations": []}, "highlightText": "", "language": "english", "persons": [], "text": "We have stayed at the Moliere a few times. Great small hotel and just a few min walk to the main central places. Clean rooms but a bit small, as you would expect in Paris.\nFantastic entertainment just a round the corner that we can recommend.", "external_links": [], "published": "2017-03-26T03:00:00.000+03:00", "crawled": "2017-03-27T13:29:17.272+03:00", "highlightTitle": ""}