{"organizations": [], "uuid": "f47ec5b15d7e5c69f7a0ba6065b927d292547633", "thread": {"social": {"gplus": {"shares": 0}, "pinterest": {"shares": 0}, "vk": {"shares": 0}, "linkedin": {"shares": 0}, "facebook": {"likes": 0, "shares": 0, "comments": 0}, "stumbledupon": {"shares": 0}}, "site_full": "www.tripadvisor.com", "main_image": "https://media-cdn.tripadvisor.com/media/photo-s/09/23/ff/0a/the-kensington-hotel.jpg", "site_section": "https://www.tripadvisor.com/Hotel_Review-g186338-d1371050-Reviews-or20-The_Kensington-London_England.html", "section_title": "The Kensington - UPDATED 2017 Hotel Reviews &amp; Price Comparison (London, England) - TripAdvisor", "url": "https://www.tripadvisor.com/ShowUserReviews-g186338-d1371050-r465060437-The_Kensington-London_England.html", "country": "US", "domain_rank": 189, "title": "Fine stay", "performance_score": 0, "site": "tripadvisor.com", "participants_count": 2, "title_full": "Fine stay - Review of The Kensington, London, England - TripAdvisor", "spam_score": 0.023, "site_type": "discussions", "published": "2017-03-06T02:00:00.000+02:00", "replies_count": 1, "uuid": "f47ec5b15d7e5c69f7a0ba6065b927d292547633"}, "author": "anitamyers20", "url": "https://www.tripadvisor.com/ShowUserReviews-g186338-d1371050-r465060437-The_Kensington-London_England.html", "ord_in_thread": 0, "title": "Fine stay", "locations": [], "entities": {"persons": [], "locations": [], "organizations": []}, "highlightText": "", "language": "english", "persons": [], "text": "If you're looking for a quiet, comfortable and convenient place to stay while you travel in London, this place it is! Staff here are the loveliest, the hotel was beautiful, newly furnished, and super clean! The staff made our stay very enjoyable especially Martyn and George The bed is definitely a highlight (so comfortable after a long day out). We wished that we were able to stay longer but we will definitely book here again when we come back!", "external_links": [], "published": "2017-03-06T02:00:00.000+02:00", "crawled": "2017-03-31T16:55:14.371+03:00", "highlightTitle": ""}