{"organizations": [], "uuid": "4ee19e7d0681e84f59e4d87ce84c7d69cbad0503", "thread": {"social": {"gplus": {"shares": 0}, "pinterest": {"shares": 0}, "vk": {"shares": 0}, "linkedin": {"shares": 0}, "facebook": {"likes": 0, "shares": 0, "comments": 0}, "stumbledupon": {"shares": 0}}, "site_full": "www.tripadvisor.com", "main_image": "https://media-cdn.tripadvisor.com/media/photo-s/06/6f/03/e9/guest-room.jpg", "site_section": "https://www.tripadvisor.com/Hotel_Review-g187147-d234633-Reviews-or5-Hotel_Residence_Foch-Paris_Ile_de_France.html", "section_title": "Hotel Residence Foch - UPDATED 2017 Reviews &amp; Price Comparison (Paris, France) - TripAdvisor", "url": "https://www.tripadvisor.com/ShowUserReviews-g187147-d234633-r466242193-Hotel_Residence_Foch-Paris_Ile_de_France.html", "country": "US", "domain_rank": 189, "title": "A short visit in Paris. It was a wedding gift.", "performance_score": 0, "site": "tripadvisor.com", "participants_count": 2, "title_full": "A short visit in Paris. It was a wedding gift. - Review of Hotel Residence Foch, Paris, France - TripAdvisor", "spam_score": 0.0, "site_type": "discussions", "published": "2017-03-11T02:00:00.000+02:00", "replies_count": 1, "uuid": "4ee19e7d0681e84f59e4d87ce84c7d69cbad0503"}, "author": "mariaj832017", "url": "https://www.tripadvisor.com/ShowUserReviews-g187147-d234633-r466242193-Hotel_Residence_Foch-Paris_Ile_de_France.html", "ord_in_thread": 0, "title": "A short visit in Paris. It was a wedding gift.", "locations": [], "entities": {"persons": [], "locations": [], "organizations": []}, "highlightText": "", "language": "english", "persons": [], "text": "The highlight of the place is the staff. Their service is absolutely outstanding. They are very nice and helpful. The hotel is located in a very quiet but still pretty central part of Paris (very close to Champs-Elysees).", "external_links": [], "published": "2017-03-11T02:00:00.000+02:00", "crawled": "2017-03-28T01:54:05.907+03:00", "highlightTitle": ""}