{"organizations": [], "uuid": "08bf8d7db04d351b14fc070cb116104c28addd3b", "thread": {"social": {"gplus": {"shares": 0}, "pinterest": {"shares": 0}, "vk": {"shares": 0}, "linkedin": {"shares": 0}, "facebook": {"likes": 0, "shares": 0, "comments": 0}, "stumbledupon": {"shares": 0}}, "site_full": "www.tripadvisor.com", "main_image": "https://media-cdn.tripadvisor.com/media/photo-s/02/55/e2/f5/conservatory.jpg", "site_section": "https://www.tripadvisor.com/Hotel_Review-g186338-d192064-Reviews-The_Chesterfield_Mayfair-London_England.html", "section_title": "The Chesterfield Mayfair - UPDATED 2017 Hotel Reviews &amp; Price Comparison (London, England) - TripAdvisor", "url": "https://www.tripadvisor.com/ShowUserReviews-g186338-d192064-r469451949-The_Chesterfield_Mayfair-London_England.html", "country": "US", "domain_rank": 189, "title": "A light evening snack", "performance_score": 0, "site": "tripadvisor.com", "participants_count": 1, "title_full": "A light evening snack - Review of The Chesterfield Mayfair, London, England - TripAdvisor", "spam_score": 0.0, "site_type": "discussions", "published": "2017-03-22T02:00:00.000+02:00", "replies_count": 0, "uuid": "08bf8d7db04d351b14fc070cb116104c28addd3b"}, "author": "Wildthing58", "url": "https://www.tripadvisor.com/ShowUserReviews-g186338-d192064-r469451949-The_Chesterfield_Mayfair-London_England.html", "ord_in_thread": 0, "title": "A light evening snack", "locations": [], "entities": {"persons": [], "locations": [], "organizations": []}, "highlightText": "", "language": "english", "persons": [], "text": "Really nice atmosphere in the terrace bar along with a fine selection of home made nibbles ranging from sausage rolls, chicken on sticks, toasted sandwiches etc etc. Washed down with a few glasses of cold beer or the specially Bouchard Finlayson fine wines from Red Carnation from RSA.", "external_links": ["https://static.tacdn.com/img2/x.gif"], "published": "2017-03-22T02:00:00.000+02:00", "crawled": "2017-03-26T20:03:40.786+03:00", "highlightTitle": ""}