{"organizations": [], "uuid": "f828077e42b1df5c46e07ef78266454139f2022c", "thread": {"social": {"gplus": {"shares": 0}, "pinterest": {"shares": 0}, "vk": {"shares": 0}, "linkedin": {"shares": 0}, "facebook": {"likes": 0, "shares": 0, "comments": 0}, "stumbledupon": {"shares": 0}}, "site_full": "www.tripadvisor.com", "main_image": "https://media-cdn.tripadvisor.com/media/photo-s/06/a5/c9/fa/ruskin-hotel.jpg", "site_section": "https://www.tripadvisor.com/Hotel_Review-g186338-d3578909-Reviews-Ruskin_Hotel-London_England.html", "section_title": "Ruskin Hotel - UPDATED 2017 Reviews &amp; Price Comparison (London, England) - TripAdvisor", "url": "https://www.tripadvisor.com/ShowUserReviews-g186338-d3578909-r465262782-Ruskin_Hotel-London_England.html", "country": "US", "domain_rank": 189, "title": "An absolute gem of a find!!", "performance_score": 0, "site": "tripadvisor.com", "participants_count": 2, "title_full": "An absolute gem of a find!! - Review of Ruskin Hotel, London, England - TripAdvisor", "spam_score": 0.0, "site_type": "discussions", "published": "2017-03-07T02:00:00.000+02:00", "replies_count": 1, "uuid": "f828077e42b1df5c46e07ef78266454139f2022c"}, "author": "Helen F", "url": "https://www.tripadvisor.com/ShowUserReviews-g186338-d3578909-r465262782-Ruskin_Hotel-London_England.html", "ord_in_thread": 0, "title": "An absolute gem of a find!!", "locations": [], "entities": {"persons": [], "locations": [], "organizations": []}, "highlightText": "", "language": "english", "persons": [], "text": "Last minute booking by a friend who upgraded her single to a twin, no problem. Lovely quiet and clean room, comfy bed and good facilities. Breakfast filling and tasty. What more could you want? Would definitely book again!", "external_links": [], "published": "2017-03-07T02:00:00.000+02:00", "crawled": "2017-03-31T21:21:27.804+03:00", "highlightTitle": ""}