{"organizations": [], "uuid": "b7980b90f5758cd628c6884234756eeccce5ac91", "thread": {"social": {"gplus": {"shares": 0}, "pinterest": {"shares": 0}, "vk": {"shares": 0}, "linkedin": {"shares": 0}, "facebook": {"likes": 0, "shares": 0, "comments": 0}, "stumbledupon": {"shares": 0}}, "site_full": "www.tripadvisor.com", "main_image": "https://media-cdn.tripadvisor.com/media/photo-s/0e/bd/6a/2a/lenox-montparnasse.jpg", "site_section": "https://www.tripadvisor.com/Hotel_Review-g187147-d235575-Reviews-Lenox_Montparnasse-Paris_Ile_de_France.html", "section_title": "Lenox Montparnasse - UPDATED 2017 Hotel Reviews &amp; Price Comparison (Paris, France) - TripAdvisor", "url": "https://www.tripadvisor.com/ShowUserReviews-g187147-d235575-r464026414-Lenox_Montparnasse-Paris_Ile_de_France.html", "country": "US", "domain_rank": 189, "title": "Excellent - Review", "performance_score": 0, "site": "tripadvisor.com", "participants_count": 1, "title_full": "Excellent - Review of Lenox Montparnasse, Paris, France - TripAdvisor", "spam_score": 0.001, "site_type": "discussions", "published": "2017-03-02T02:00:00.000+02:00", "replies_count": 0, "uuid": "b7980b90f5758cd628c6884234756eeccce5ac91"}, "author": "davidbates37", "url": "https://www.tripadvisor.com/ShowUserReviews-g187147-d235575-r464026414-Lenox_Montparnasse-Paris_Ile_de_France.html", "ord_in_thread": 0, "title": "Excellent - Review", "locations": [], "entities": {"persons": [], "locations": [], "organizations": []}, "highlightText": "", "language": "english", "persons": [], "text": "The hotel was beautiful and we enjoyed our stay and the staff were very helpful and kind I would definitely stay at this hotel again if we go to Paris they all so help us in booking out taxi back to the airport thank you very much for this", "external_links": [], "published": "2017-03-02T02:00:00.000+02:00", "crawled": "2017-03-27T04:30:23.170+03:00", "highlightTitle": ""}